odoo/addons/sale_order_blanket_order_stock_prebook_release/README.rst
odoo/addons/sale_order_blanket_order_stock_prebook_release/__init__.py
odoo/addons/sale_order_blanket_order_stock_prebook_release/__manifest__.py
odoo/addons/sale_order_blanket_order_stock_prebook_release/hooks.py
odoo/addons/sale_order_blanket_order_stock_prebook_release/i18n/it.po
odoo/addons/sale_order_blanket_order_stock_prebook_release/i18n/sale_order_blanket_order_stock_prebook_release.pot
odoo/addons/sale_order_blanket_order_stock_prebook_release/models/__init__.py
odoo/addons/sale_order_blanket_order_stock_prebook_release/models/sale_order.py
odoo/addons/sale_order_blanket_order_stock_prebook_release/models/sale_order_line.py
odoo/addons/sale_order_blanket_order_stock_prebook_release/readme/CONTEXT.md
odoo/addons/sale_order_blanket_order_stock_prebook_release/readme/CONTRIBUTORS.md
odoo/addons/sale_order_blanket_order_stock_prebook_release/readme/CREDITS.md
odoo/addons/sale_order_blanket_order_stock_prebook_release/readme/DESCRIPTION.md
odoo/addons/sale_order_blanket_order_stock_prebook_release/static/description/icon.png
odoo/addons/sale_order_blanket_order_stock_prebook_release/static/description/index.html
odoo/addons/sale_order_blanket_order_stock_prebook_release/tests/__init__.py
odoo/addons/sale_order_blanket_order_stock_prebook_release/tests/common.py
odoo/addons/sale_order_blanket_order_stock_prebook_release/tests/test_sale_order_blanket_order_stock_prebook_release.py
odoo_addon_sale_order_blanket_order_stock_prebook_release-16.0.1.1.0.2.dist-info/METADATA
odoo_addon_sale_order_blanket_order_stock_prebook_release-16.0.1.1.0.2.dist-info/WHEEL
odoo_addon_sale_order_blanket_order_stock_prebook_release-16.0.1.1.0.2.dist-info/top_level.txt
odoo_addon_sale_order_blanket_order_stock_prebook_release-16.0.1.1.0.2.dist-info/RECORD
